crekai_verify/__init__.py
crekai_verify/core.py
crekai_verify-2.0.0.dist-info/METADATA
crekai_verify-2.0.0.dist-info/WHEEL
crekai_verify-2.0.0.dist-info/top_level.txt
crekai_verify-2.0.0.dist-info/RECORD
