Metadata-Version: 2.4
Name: crekai-verify
Version: 2.0.0
Summary: Universal CrekAI Verification Tool for Colab
Home-page: https://github.com/thevixhal/crekai-verify
Author: Vishal
Author-email: realvixhal@gmail.com
Classifier: Programming Language :: Python :: 3
Classifier: License :: OSI Approved :: MIT License
Classifier: Operating System :: OS Independent
Requires-Python: >=3.7
Requires-Dist: requests>=2.20.0
Dynamic: author
Dynamic: author-email
Dynamic: classifier
Dynamic: description
Dynamic: description-content-type
Dynamic: home-page
Dynamic: requires-dist
Dynamic: requires-python
Dynamic: summary
